LICENSE
README.md
setup.py
coota/__init__.py
coota/configuration.py
coota/generator.py
coota/generator_sequence.py
coota/sets.py
coota.egg-info/PKG-INFO
coota.egg-info/SOURCES.txt
coota.egg-info/dependency_links.txt
coota.egg-info/requires.txt
coota.egg-info/top_level.txt
coota/preset/__init__.py
coota/preset/generator.py
coota/preset/sets.py
coota/toolkit/__init__.py
coota/toolkit/operator.py
coota/toolkit/time.py
coota/toolkit/visualization.py