Metadata-Version: 2.1
Name: coota
Version: 1.0.3
Summary: A powerful data-generating library.
Home-page: https://github.com/ATATC/COOTA
Author: ATATC
Author-email: futerry@outlook.com
License: Apache License 2.0
Platform: UNKNOWN
License-File: LICENSE
